Workbook
Name aporte: Plan1!$D$15
Name patrimonio: Plan1!$D$18
Name qtde_anos: Plan1!$D$16
Name rendimento_carteira: Plan1!$D$11
Name salario: Plan1!$D$10
Name sugestao_investimento: Plan1!$D$12
Name taxa_mensal: Plan1!$D$17

Sheet Plan1
B9: CONFIGURAÇÕES
B10: Salário | D10: 4000
B11: Rendimento Carteira | D11: 0.009
B12: Sugestão de Investimento | D12: =D10*30% -> 1200
B14: INVESTIMENTO MENSAL
B15: Quanto investir por mês? | D15: 1200
B16: Por Quantos Anos? | D16: 10
B17: taxa de Rendimento mensal? | D17: 0.01079
B18: Patrimônio acumulado? | D18: =FV(taxa_mensal,qtde_anos*12,aporte*-1) -> 291941.06
B19: Dividendos Mensais? | D19: =patrimonio*rendimento_carteira -> 2627.4695
B21: CENÁRIOS | D21: DIVIDENDOS
A22: 2 | B22: Quanto em 2 Anos? | C22: =FV(taxa_mensal,$A22*12,aporte*-1) -> 32673.153 | D22: =C22*rendimento_carteira -> 294.05837
A23: 5 | B23: Quanto em 5 Anos? | C23: =FV(taxa_mensal,$A23*12,aporte*-1) -> 100532.3 | D23: =C23*rendimento_carteira -> 904.79067
A24: 10 | B24: Quanto em 10 Anos? | C24: =FV(taxa_mensal,$A24*12,aporte*-1) -> 291941.06 | D24: =C24*rendimento_carteira -> 2627.4695
A25: 20 | B25: Quanto em 20 Anos? | C25: =FV(taxa_mensal,$A25*12,aporte*-1) -> 1350238.1 | D25: =C25*rendimento_carteira -> 12152.143
A26: 30 | B26: Quanto em 30 Anos? | C26: =FV(taxa_mensal,$A26*12,aporte*-1) -> 5186603.6 | D26: =C26*rendimento_carteira -> 46679.432
B29: PERFIL | C29: Moderado
B30: VALOR A SER INVESTIDO POR MÊS | C30: =aporte -> 1200
B32: TIPO DE FII | C32: Percentual Sugerido | D32: Valores
B33: PAPEL | C33: =VLOOKUP($C$29&"-"&B33,Plan2!$A$2:$D$20,4,FALSE) -> 0.32 | D33: =C33*$C$30 -> 384
B34: TIJOLOS | C34: =VLOOKUP($C$29&"-"&B34,Plan2!$A$2:$D$20,4,FALSE) -> 0.35 | D34: =C34*$C$30 -> 420
B35: HÍBRIDOS | C35: =VLOOKUP($C$29&"-"&B35,Plan2!$A$2:$D$20,4,FALSE) -> 0.08 | D35: =C35*$C$30 -> 96
B36: FOFs | C36: =VLOOKUP($C$29&"-"&B36,Plan2!$A$2:$D$20,4,FALSE) -> 0.05 | D36: =C36*$C$30 -> 60
B37: DESENVOLVIMENTO | C37: =VLOOKUP($C$29&"-"&B37,Plan2!$A$2:$D$20,4,FALSE) -> 0.1 | D37: =C37*$C$30 -> 120
B38: HOTELARIAS | C38: =VLOOKUP($C$29&"-"&B38,Plan2!$A$2:$D$20,4,FALSE) -> 0.1 | D38: =C38*$C$30 -> 120
D39: =SUM(D33:D38) -> 1200

Sheet Plan2
A2: CHAVE | B2: PERFIL | C2: TIPO DE FII | D2: %
A3: =B$3&"-"&C3 -> Conservador-PAPEL | B3: Conservador | C3: PAPEL | D3: 0.3
A4: =B$3&"-"&C4 -> Conservador-TIJOLOS | B4: Conservador | C4: TIJOLOS | D4: 0.5 | H4: %
A5: =B$3&"-"&C5 -> Conservador-HÍBRIDOS | B5: Conservador | C5: HÍBRIDOS | D5: 0.1 | G5: Moderado-TIJOLOS | H5: =VLOOKUP(G5,$A$2:$D$20,4,FALSE) -> 0.35
A6: =B$3&"-"&C6 -> Conservador-FOFs | B6: Conservador | C6: FOFs | D6: 0.1
A7: =B$3&"-"&C7 -> Conservador-DESENVOLVIMENTO | B7: Conservador | C7: DESENVOLVIMENTO | D7: 0
A8: =B$3&"-"&C8 -> Conservador-HOTELARIAS | B8: Conservador | C8: HOTELARIAS | D8: 0
A9: =B$9&"-"&C9 -> Moderado-PAPEL | B9: Moderado | C9: PAPEL | D9: 0.32
A10: =B$9&"-"&C10 -> Moderado-TIJOLOS | B10: Moderado | C10: TIJOLOS | D10: 0.35
A11: =B$9&"-"&C11 -> Moderado-HÍBRIDOS | B11: Moderado | C11: HÍBRIDOS | D11: 0.08
A12: =B$9&"-"&C12 -> Moderado-FOFs | B12: Moderado | C12: FOFs | D12: 0.05
A13: =B$9&"-"&C13 -> Moderado-DESENVOLVIMENTO | B13: Moderado | C13: DESENVOLVIMENTO | D13: 0.1
A14: =B$9&"-"&C14 -> Moderado-HOTELARIAS | B14: Moderado | C14: HOTELARIAS | D14: 0.1
A15: =$B$15&"-"&C15 -> Agressivo-PAPEL | B15: Agressivo | C15: PAPEL | D15: 0.5
A16: =$B$15&"-"&C16 -> Agressivo-TIJOLOS | B16: Agressivo | C16: TIJOLOS | D16: 0.1
A17: =$B$15&"-"&C17 -> Agressivo-HÍBRIDOS | B17: Agressivo | C17: HÍBRIDOS | D17: 0.05
A18: =$B$15&"-"&C18 -> Agressivo-FOFs | B18: Agressivo | C18: FOFs | D18: 0.05
A19: =$B$15&"-"&C19 -> Agressivo-DESENVOLVIMENTO | B19: Agressivo | C19: DESENVOLVIMENTO | D19: 0.2
A20: =$B$15&"-"&C20 -> Agressivo-HOTELARIAS | B20: Agressivo | C20: HOTELARIAS | D20: 0.1
